phonemizer/__init__.py
phonemizer/logger.py
phonemizer/main.py
phonemizer/phonemize.py
phonemizer/punctuation.py
phonemizer/separator.py
phonemizer/utils.py
phonemizer/version.py
phonemizer/backend/__init__.py
phonemizer/backend/base.py
phonemizer/backend/segments.py
phonemizer/backend/espeak/__init__.py
phonemizer/backend/espeak/api.py
phonemizer/backend/espeak/base.py
phonemizer/backend/espeak/espeak.py
phonemizer/backend/espeak/language_switch.py
phonemizer/backend/espeak/mbrola.py
phonemizer/backend/espeak/voice.py
phonemizer/backend/espeak/words_mismatch.py
phonemizer/backend/espeak/wrapper.py
phonemizer/backend/festival/__init__.py
phonemizer/backend/festival/festival.py
phonemizer/backend/festival/lispy.py
phonemizer/share/festival/phonemize.scm
phonemizer/share/segments/chintang.g2p
phonemizer/share/segments/cree.g2p
phonemizer/share/segments/inuktitut.g2p
phonemizer/share/segments/japanese.g2p
phonemizer/share/segments/sesotho.g2p
phonemizer/share/segments/yucatec.g2p
test/__init__.py
test/test_espeak.py
test/test_espeak_lang_switch.py
test/test_espeak_word_mismatch.py
test/test_espeak_wrapper.py
test/test_festival.py
test/test_import.py
test/test_main.py
test/test_mbrola.py
test/test_phonemize.py
test/test_punctuation.py
test/test_segments.py
test/test_separator.py
test/test_utils.py
phonemizer-3.2.1.dist-info/LICENSE
phonemizer-3.2.1.dist-info/METADATA
phonemizer-3.2.1.dist-info/WHEEL
phonemizer-3.2.1.dist-info/entry_points.txt
phonemizer-3.2.1.dist-info/top_level.txt
phonemizer-3.2.1.dist-info/zip-safe
phonemizer-3.2.1.dist-info/RECORD
