Metadata-Version: 2.1
Name: phonemizer
Version: 3.2.1
Summary:  Simple text to phones converter for multiple languages
Home-page: https://github.com/bootphon/phonemizer
Author: Mathieu Bernard
Author-email: mathieu.a.bernard@inria.fr
License: GPL3
Keywords: linguistics G2P phone festival espeak TTS
Platform: UNKNOWN
Classifier: Programming Language :: Python :: 3
Classifier: License :: OSI Approved :: GNU General Public License v3 or later (GPLv3+)
Classifier: Operating System :: OS Independent
Requires-Python: >=3.6
Provides-Extra: tests
Provides-Extra: doc
License-File: LICENSE
